driven_helloworld/_init__.py
driven_helloworld/greet.py
driven_helloworld511-0.0.2.dist-info/METADATA
driven_helloworld511-0.0.2.dist-info/WHEEL
driven_helloworld511-0.0.2.dist-info/top_level.txt
driven_helloworld511-0.0.2.dist-info/RECORD
