Metadata-Version: 2.1
Name: driven-helloworld511
Version: 0.0.2
Summary: hello world
Home-page: UNKNOWN
Author: zhidongni
Maintainer: zhidongni
License: UNKNOWN
Platform: UNKNOWN
